rlvoice/__init__.py
rlvoice/driver.py
rlvoice/engine.py
rlvoice/six.py
rlvoice/voice.py
rlvoice/drivers/__init__.py
rlvoice/drivers/_espeak.py
rlvoice/drivers/dummy.py
rlvoice/drivers/espeak.py
rlvoice/drivers/nsss.py
rlvoice/drivers/sapi5.py
rlvoice-1.0.0.dist-info/LICENSE
rlvoice-1.0.0.dist-info/METADATA
rlvoice-1.0.0.dist-info/WHEEL
rlvoice-1.0.0.dist-info/top_level.txt
rlvoice-1.0.0.dist-info/RECORD
