Metadata-Version: 2.1
Name: rlvoice
Version: 1.0.0
Summary: Text to Speech (TTS) library for Python 3. Works without internet connection or delay. Supports multiple TTS engines, including Sapi5, nsss, and espeak.
Home-page: https://github.com/Akul-AI/rlvoice
Author: AkulAI
Author-email: akulgoelstudios@gmail.com
Keywords: pyttsx,ivona,pyttsx for python3,TTS for python3,rlvoice,text to speech for python,tts,text to speech,speech,speech synthesis,offline text to speech,offline tts,gtts
Classifier: Intended Audience :: End Users/Desktop
Classifier: Intended Audience :: Developers
Classifier: Intended Audience :: Information Technology
Classifier: Intended Audience :: System Administrators
Classifier: Operating System :: MacOS :: MacOS X
Classifier: Operating System :: Microsoft :: Windows
Classifier: Operating System :: POSIX
Classifier: License :: OSI Approved :: Mozilla Public License 2.0 (MPL 2.0)
Classifier: Programming Language :: Python :: 3
Classifier: Programming Language :: Python :: 3.5
Classifier: Programming Language :: Python :: 3.6
Classifier: Programming Language :: Python :: 3.7
License-File: LICENSE
